odoo/addons/shopfloor_reception_packaging_dimension/README.rst
odoo/addons/shopfloor_reception_packaging_dimension/__init__.py
odoo/addons/shopfloor_reception_packaging_dimension/__manifest__.py
odoo/addons/shopfloor_reception_packaging_dimension/hooks.py
odoo/addons/shopfloor_reception_packaging_dimension/i18n/it.po
odoo/addons/shopfloor_reception_packaging_dimension/i18n/shopfloor_reception_packaging_dimension.pot
odoo/addons/shopfloor_reception_packaging_dimension/models/__init__.py
odoo/addons/shopfloor_reception_packaging_dimension/models/product_packaging_level.py
odoo/addons/shopfloor_reception_packaging_dimension/models/shopfloor_menu.py
odoo/addons/shopfloor_reception_packaging_dimension/readme/CONTRIBUTORS.md
odoo/addons/shopfloor_reception_packaging_dimension/readme/DESCRIPTION.md
odoo/addons/shopfloor_reception_packaging_dimension/services/__init__.py
odoo/addons/shopfloor_reception_packaging_dimension/services/reception.py
odoo/addons/shopfloor_reception_packaging_dimension/static/description/icon.png
odoo/addons/shopfloor_reception_packaging_dimension/static/description/index.html
odoo/addons/shopfloor_reception_packaging_dimension/tests/__init__.py
odoo/addons/shopfloor_reception_packaging_dimension/tests/test_set_package_dimension.py
odoo/addons/shopfloor_reception_packaging_dimension/views/product_packaging_level.xml
odoo/addons/shopfloor_reception_packaging_dimension/views/shopfloor_menu.xml
odoo_addon_shopfloor_reception_packaging_dimension-18.0.1.1.0.2.dist-info/METADATA
odoo_addon_shopfloor_reception_packaging_dimension-18.0.1.1.0.2.dist-info/WHEEL
odoo_addon_shopfloor_reception_packaging_dimension-18.0.1.1.0.2.dist-info/top_level.txt
odoo_addon_shopfloor_reception_packaging_dimension-18.0.1.1.0.2.dist-info/RECORD
