Metadata-Version: 2.1
Name: odoo-addon-shopfloor_reception_packaging_dimension
Version: 18.0.1.1.0.2
Requires-Python: >=3.10
Requires-Dist: odoo-addon-product_packaging_level==18.0.*
Requires-Dist: odoo-addon-shopfloor_reception==18.0.*
Requires-Dist: odoo==18.0.*
Summary: Collect Packaging Dimension from the Reception scenario
Home-page: https://github.com/OCA/stock-logistics-shopfloor
License: AGPL-3
Author: Camptocamp, Odoo Community Association (OCA)
Author-email: support@odoo-community.org
Classifier: Programming Language :: Python
Classifier: Framework :: Odoo
Classifier: Framework :: Odoo :: 18.0
Classifier: License :: OSI Approved :: GNU Affero General Public License v3
Classifier: Development Status :: 4 - Beta
